[
  {
    "name": "Udoka Dandave",
    "email": "dandaveudoka@gmail.com",
    "message": "hello big guy hopes this works",
    "date": "2025-02-26T13:17:06.598Z"
  },
  {
    "name": "chicago",
    "email": "dandaveudoka@gmail.com",
    "message": "am so happy",
    "date": "2025-02-26T13:20:09.325Z"
  },
  {
    "name": "chicago",
    "email": "dandaveudoka@gmail.com",
    "message": "am so happy",
    "date": "2025-02-26T13:32:54.989Z",
    "userIp": "::ffff:127.0.0.1",
    "location": {
      "country": "Unknown",
      "city": "Unknown",
      "region": "Unknown",
      "isp": "Unknown",
      "timezone": "Unknown"
    }
  },
  {
    "name": "chicago",
    "email": "dandaveudoka@gmail.com",
    "message": "am so happy",
    "date": "2025-02-26T13:43:38.887Z",
    "userIp": "::ffff:127.0.0.1",
    "location": {
      "country": "Unknown",
      "city": "Unknown",
      "region": "Unknown",
      "isp": "Unknown",
      "timezone": "Unknown"
    }
  },
  {
    "name": "Dandaveudoks",
    "email": "dcndcfdvcjmfdvc@gmail.com",
    "message": "hellllo",
    "date": "2025-02-26T14:44:42.546Z",
    "userIp": "::1",
    "location": {
      "country": "Unknown",
      "city": "Unknown",
      "region": "Unknown",
      "isp": "Unknown",
      "timezone": "Unknown"
    }
  },
  {
    "name": "Dandaveudoks",
    "email": "dcndcfdvcjmfdvc@gmail.com",
    "message": "hellllo",
    "date": "2025-02-26T14:44:42.557Z",
    "userIp": "::1",
    "location": {
      "country": "Unknown",
      "city": "Unknown",
      "region": "Unknown",
      "isp": "Unknown",
      "timezone": "Unknown"
    }
  },
  {
    "name": "Dandaveudoks",
    "email": "dcndcfdvcjmfdvc@gmail.com",
    "message": "hellllo",
    "date": "2025-02-26T14:44:42.853Z",
    "userIp": "::1",
    "location": {
      "country": "Unknown",
      "city": "Unknown",
      "region": "Unknown",
      "isp": "Unknown",
      "timezone": "Unknown"
    }
  },
  {
    "name": "Dandaveudoks",
    "email": "dcndcfdvcjmfdvc@gmail.com",
    "message": "hellllo",
    "date": "2025-02-26T14:44:43.110Z",
    "userIp": "::1",
    "location": {
      "country": "Unknown",
      "city": "Unknown",
      "region": "Unknown",
      "isp": "Unknown",
      "timezone": "Unknown"
    }
  },
  {
    "name": "Dandaveudoks",
    "email": "dcndcfdvcjmfdvc@gmail.com",
    "message": "hellllo",
    "date": "2025-02-26T14:44:43.230Z",
    "userIp": "::1",
    "location": {
      "country": "Unknown",
      "city": "Unknown",
      "region": "Unknown",
      "isp": "Unknown",
      "timezone": "Unknown"
    }
  },
  {
    "name": "Dandaveudoks",
    "email": "dcndcfdvcjmfdvc@gmail.com",
    "message": "hellllo",
    "date": "2025-02-26T14:44:43.427Z",
    "userIp": "::1",
    "location": {
      "country": "Unknown",
      "city": "Unknown",
      "region": "Unknown",
      "isp": "Unknown",
      "timezone": "Unknown"
    }
  },
  {
    "name": "Dandaveudoks",
    "email": "dcndcfdvcjmfdvc@gmail.com",
    "message": "hellllo",
    "date": "2025-02-26T14:44:43.552Z",
    "userIp": "::1",
    "location": {
      "country": "Unknown",
      "city": "Unknown",
      "region": "Unknown",
      "isp": "Unknown",
      "timezone": "Unknown"
    }
  },
  {
    "name": "Dandaveudoks",
    "email": "dcndcfdvcjmfdvc@gmail.com",
    "message": "hellllo",
    "date": "2025-02-26T14:44:43.634Z",
    "userIp": "::1",
    "location": {
      "country": "Unknown",
      "city": "Unknown",
      "region": "Unknown",
      "isp": "Unknown",
      "timezone": "Unknown"
    }
  },
  {
    "name": "Dandaveudoks",
    "email": "dcndcfdvcjmfdvc@gmail.com",
    "message": "hellllo",
    "date": "2025-02-26T14:44:43.967Z",
    "userIp": "::1",
    "location": {
      "country": "Unknown",
      "city": "Unknown",
      "region": "Unknown",
      "isp": "Unknown",
      "timezone": "Unknown"
    }
  },
  {
    "name": "Dandaveudoks",
    "email": "dcndcfdvcjmfdvc@gmail.com",
    "message": "hellllo",
    "date": "2025-02-26T14:44:44.054Z",
    "userIp": "::1",
    "location": {
      "country": "Unknown",
      "city": "Unknown",
      "region": "Unknown",
      "isp": "Unknown",
      "timezone": "Unknown"
    }
  },
  {
    "name": "Dandaveudoks",
    "email": "dcndcfdvcjmfdvc@gmail.com",
    "message": "hellllo",
    "date": "2025-02-26T14:44:44.266Z",
    "userIp": "::1",
    "location": {
      "country": "Unknown",
      "city": "Unknown",
      "region": "Unknown",
      "isp": "Unknown",
      "timezone": "Unknown"
    }
  },
  {
    "name": "Dandaveudoks",
    "email": "dcndcfdvcjmfdvc@gmail.com",
    "message": "hellllo",
    "date": "2025-02-26T14:44:44.336Z",
    "userIp": "::1",
    "location": {
      "country": "Unknown",
      "city": "Unknown",
      "region": "Unknown",
      "isp": "Unknown",
      "timezone": "Unknown"
    }
  },
  {
    "name": "Dandaveudoks",
    "email": "dcndcfdvcjmfdvc@gmail.com",
    "message": "hellllo",
    "date": "2025-02-26T14:44:44.861Z",
    "userIp": "::1",
    "location": {
      "country": "Unknown",
      "city": "Unknown",
      "region": "Unknown",
      "isp": "Unknown",
      "timezone": "Unknown"
    }
  },
  {
    "name": "Dandaveudoks",
    "email": "dcndcfdvcjmfdvc@gmail.com",
    "message": "hellllo",
    "date": "2025-02-26T14:44:44.946Z",
    "userIp": "::1",
    "location": {
      "country": "Unknown",
      "city": "Unknown",
      "region": "Unknown",
      "isp": "Unknown",
      "timezone": "Unknown"
    }
  },
  {
    "name": "Dandaveudoks",
    "email": "dcndcfdvcjmfdvc@gmail.com",
    "message": "hellllo",
    "date": "2025-02-26T14:44:45.502Z",
    "userIp": "::1",
    "location": {
      "country": "Unknown",
      "city": "Unknown",
      "region": "Unknown",
      "isp": "Unknown",
      "timezone": "Unknown"
    }
  },
  {
    "name": "Dandaveudoks",
    "email": "dcndcfdvcjmfdvc@gmail.com",
    "message": "hellllo",
    "date": "2025-02-26T14:44:45.828Z",
    "userIp": "::1",
    "location": {
      "country": "Unknown",
      "city": "Unknown",
      "region": "Unknown",
      "isp": "Unknown",
      "timezone": "Unknown"
    }
  },
  {
    "name": "Dandaveudoks",
    "email": "dcndcfdvcjmfdvc@gmail.com",
    "message": "hellllo",
    "date": "2025-02-26T14:44:46.697Z",
    "userIp": "::1",
    "location": {
      "country": "Unknown",
      "city": "Unknown",
      "region": "Unknown",
      "isp": "Unknown",
      "timezone": "Unknown"
    }
  },
  {
    "name": "Dandaveudoks",
    "email": "dcndcfdvcjmfdvc@gmail.com",
    "message": "hellllo",
    "date": "2025-02-26T14:44:47.692Z",
    "userIp": "::1",
    "location": {
      "country": "Unknown",
      "city": "Unknown",
      "region": "Unknown",
      "isp": "Unknown",
      "timezone": "Unknown"
    }
  },
  {
    "name": "Dandaveudoks",
    "email": "dcndcfdvcjmfdvc@gmail.com",
    "message": "hellllo",
    "date": "2025-02-26T14:44:47.814Z",
    "userIp": "::1",
    "location": {
      "country": "Unknown",
      "city": "Unknown",
      "region": "Unknown",
      "isp": "Unknown",
      "timezone": "Unknown"
    }
  },
  {
    "name": "Dandaveudoks",
    "email": "dcndcfdvcjmfdvc@gmail.com",
    "message": "hellllo",
    "date": "2025-02-26T14:44:47.854Z",
    "userIp": "::1",
    "location": {
      "country": "Unknown",
      "city": "Unknown",
      "region": "Unknown",
      "isp": "Unknown",
      "timezone": "Unknown"
    }
  },
  {
    "name": "Dandaveudoks",
    "email": "dcndcfdvcjmfdvc@gmail.com",
    "message": "hellllo",
    "date": "2025-02-26T14:46:31.633Z",
    "userIp": "::1",
    "location": {
      "country": "Unknown",
      "city": "Unknown",
      "region": "Unknown",
      "isp": "Unknown",
      "timezone": "Unknown"
    }
  },
  {
    "name": "Dandaveudoks",
    "email": "dcndcfdvcjmfdvc@gmail.com",
    "message": "hellllo",
    "date": "2025-02-26T14:46:46.363Z",
    "userIp": "::1",
    "location": {
      "country": "Unknown",
      "city": "Unknown",
      "region": "Unknown",
      "isp": "Unknown",
      "timezone": "Unknown"
    }
  },
  {
    "name": "Dandaveudoks",
    "email": "dcndcfdvcjmfdvc@gmail.com",
    "message": "hellllo",
    "date": "2025-02-26T14:46:46.697Z",
    "userIp": "::1",
    "location": {
      "country": "Unknown",
      "city": "Unknown",
      "region": "Unknown",
      "isp": "Unknown",
      "timezone": "Unknown"
    }
  },
  {
    "name": "Dandaveudoks",
    "email": "dcndcfdvcjmfdvc@gmail.com",
    "message": "hellllo",
    "date": "2025-02-26T14:48:59.887Z",
    "userIp": "::1",
    "location": {
      "country": "Unknown",
      "city": "Unknown",
      "region": "Unknown",
      "isp": "Unknown",
      "timezone": "Unknown"
    }
  },
  {
    "name": "Dandaveudoks",
    "email": "dcndcfdvcjmfdvc@gmail.com",
    "message": "hellllo",
    "date": "2025-02-26T14:49:01.848Z",
    "userIp": "::1",
    "location": {
      "country": "Unknown",
      "city": "Unknown",
      "region": "Unknown",
      "isp": "Unknown",
      "timezone": "Unknown"
    }
  },
  {
    "name": "Dandaveudoks",
    "email": "dcndcfdvcjmfdvc@gmail.com",
    "message": "hellllo",
    "date": "2025-02-26T14:49:08.279Z",
    "userIp": "::1",
    "location": {
      "country": "Unknown",
      "city": "Unknown",
      "region": "Unknown",
      "isp": "Unknown",
      "timezone": "Unknown"
    }
  },
  {
    "name": "Dandaveudoks",
    "email": "dcndcfdvcjmfdvc@gmail.com",
    "message": "hellllo",
    "date": "2025-02-26T14:51:37.966Z",
    "userIp": "::1",
    "location": {
      "country": "Unknown",
      "city": "Unknown",
      "region": "Unknown",
      "isp": "Unknown",
      "timezone": "Unknown"
    }
  },
  {
    "name": "kkffffkkkkkkkkkkkk",
    "email": "dcndcfdfvcjmfdvc@gmail.com",
    "message": "hellllof",
    "date": "2025-02-26T14:52:58.241Z",
    "userIp": "::1",
    "location": {
      "country": "Unknown",
      "city": "Unknown",
      "region": "Unknown",
      "isp": "Unknown",
      "timezone": "Unknown"
    }
  },
  {
    "name": "Dandaveudoks",
    "email": "dcndcfdvcjmfdvc@gmail.com",
    "message": "hellllo",
    "date": "2025-02-26T14:54:14.969Z",
    "userIp": "::1",
    "location": {
      "country": "Unknown",
      "city": "Unknown",
      "region": "Unknown",
      "isp": "Unknown",
      "timezone": "Unknown"
    }
  },
  {
    "name": "Dandaveudoks",
    "email": "dcndcfdvcjmfdvc@gmail.com",
    "message": "hellllo",
    "date": "2025-02-26T14:55:51.978Z",
    "userIp": "::1",
    "location": {
      "country": "Unknown",
      "city": "Unknown",
      "region": "Unknown",
      "isp": "Unknown",
      "timezone": "Unknown"
    }
  },
  {
    "name": "chicago",
    "email": "dan@gmail.com",
    "message": "hu",
    "date": "2025-02-26T14:57:52.479Z",
    "userIp": "::1",
    "location": {
      "country": "Unknown",
      "city": "Unknown",
      "region": "Unknown",
      "isp": "Unknown",
      "timezone": "Unknown"
    }
  },
  {
    "name": "chicago",
    "email": "dan@gmail.com",
    "message": "hu",
    "date": "2025-02-26T14:57:53.150Z",
    "userIp": "::1",
    "location": {
      "country": "Unknown",
      "city": "Unknown",
      "region": "Unknown",
      "isp": "Unknown",
      "timezone": "Unknown"
    }
  },
  {
    "name": "Dandaveudoks",
    "email": "dcndcfdvcjmfdvc@gmail.com",
    "message": "hellllo",
    "date": "2025-02-26T15:15:45.044Z"
  },
  {
    "name": "Dandaveudoks",
    "email": "dcndcfdvcjmfdvc@gmail.com",
    "message": "bbbbbbbbbbbbbbbbbbbbbb",
    "date": "2025-02-26T15:18:01.701Z"
  },
  {
    "name": "Dandaveudoka",
    "email": "onyekwerehenry@gmail.com",
    "message": "i love your site",
    "date": "2025-02-26T18:06:52.348Z"
  },
  {
    "name": "Dandaveudoka",
    "email": "onyekwerehenry@gmail.com",
    "message": "i love your site",
    "date": "2025-02-26T18:07:23.814Z"
  },
  {
    "name": "Dandaveudoka",
    "email": "onyekwerehenry@gmail.com",
    "message": "i love your site",
    "date": "2025-02-26T18:07:24.189Z"
  },
  {
    "name": "Dandaveudoka",
    "email": "onyekwerehenry@gmail.com",
    "message": "i love your site",
    "date": "2025-02-26T18:07:24.368Z"
  },
  {
    "name": "dandy",
    "email": "davetechinnovation@gmail.com",
    "message": "hiiiiiii",
    "date": "2025-02-26T18:15:15.883Z"
  },
  {
    "name": "Dandaveudoka",
    "email": "onyekwerehenry@gmail.com",
    "message": "hello",
    "date": "2025-02-26T18:28:10.108Z"
  },
  {
    "name": "Onyekwere Henry",
    "email": "onyekwerehenry@gmail.com",
    "message": "i Soo much love ur contact form",
    "date": "2025-02-26T18:51:30.610Z"
  },
  {
    "name": "Onyekwere Henry",
    "email": "onyekwerehenry@gmail.com",
    "message": "I soo much l;ove ur site boss",
    "date": "2025-02-26T18:51:51.451Z"
  },
  {
    "name": "Onyekwere Henry",
    "email": "onyekwerehenry@gmail.com",
    "message": "I love ur site soo much",
    "date": "2025-02-26T18:54:15.127Z"
  },
  {
    "name": "Onyekwere Henry",
    "email": "onyekwerehenry@gmail.com",
    "date": "2025-02-27T13:08:53.133Z"
  },
  {
    "name": "Onyekwere Henry",
    "email": "onyekwerehenry@gmail.com",
    "date": "2025-02-27T13:08:53.806Z"
  },
  {
    "name": "Onyekwere Henry",
    "email": "onyekwerehenry@gmail.com",
    "date": "2025-02-27T13:10:16.517Z"
  },
  {
    "name": "Onyekwere Henry",
    "email": "onyekwerehenry@gmail.com",
    "date": "2025-02-27T13:10:17.269Z"
  },
  {
    "name": "Onyekwere Henry",
    "email": "onyekwerehenry@gmail.com",
    "date": "2025-02-27T13:13:21.655Z"
  },
  {
    "name": "Onyekwere Henry",
    "email": "onyekwerehenry@gmail.com",
    "date": "2025-02-27T13:13:22.346Z"
  },
  {
    "name": "Onyekwere Henry",
    "email": "onyekwerehenry@gmail.com",
    "date": "2025-02-27T13:15:23.188Z"
  },
  {
    "name": "Onyekwere Henry",
    "email": "onyekwerehenry@gmail.com",
    "date": "2025-02-27T13:15:23.863Z"
  },
  {
    "name": "Onyekwere Henry",
    "email": "onyekwerehenry@gmail.com",
    "date": "2025-02-27T13:18:25.544Z"
  },
  {
    "name": "Onyekwere Henry",
    "email": "onyekwerehenry@gmail.com",
    "date": "2025-02-27T13:18:26.323Z"
  },
  {
    "name": "udolka",
    "email": "udolka@gmail.com",
    "date": "2025-02-27T13:21:46.356Z"
  },
  {
    "name": "udolka",
    "email": "udolka@gmail.com",
    "date": "2025-02-27T13:22:36.217Z"
  },
  {
    "name": "udolka",
    "email": "udolka@gmail.com",
    "date": "2025-02-27T13:22:38.660Z"
  },
  {
    "name": "udolka",
    "email": "udolka@gmail.com",
    "date": "2025-02-27T13:22:39.439Z"
  },
  {
    "name": "udolka",
    "email": "udolka@gmail.com",
    "date": "2025-02-27T13:22:40.140Z"
  },
  {
    "name": "udolka",
    "email": "udolka@gmail.com",
    "date": "2025-02-27T13:22:40.819Z"
  },
  {
    "name": "udolka",
    "email": "udolka@gmail.com",
    "date": "2025-02-27T13:22:41.630Z"
  },
  {
    "name": "udolka",
    "email": "udolka@gmail.com",
    "date": "2025-02-27T13:22:42.333Z"
  },
  {
    "name": "udolka",
    "email": "udolka@gmail.com",
    "date": "2025-02-27T13:22:42.979Z"
  },
  {
    "name": "udolka",
    "email": "udolka@gmail.com",
    "date": "2025-02-27T13:23:06.252Z"
  },
  {
    "name": "Onyekwere Henry",
    "email": "onyekwerehenry@gmail.com",
    "date": "2025-02-27T13:26:29.265Z"
  },
  {
    "name": "Onyekwere Henry",
    "email": "onyekwerehenry@gmail.com",
    "date": "2025-02-27T13:26:30.234Z"
  },
  {
    "name": "Onyekwere Henry",
    "email": "onyekwerehenry@gmail.com",
    "date": "2025-02-27T13:30:06.270Z"
  },
  {
    "name": "Onyekwere Henry",
    "email": "onyekwerehenry@gmail.com",
    "date": "2025-02-27T13:30:06.989Z"
  },
  {
    "name": "dd",
    "email": "onyekwerehenry@gmail.com",
    "date": "2025-02-27T13:31:26.895Z"
  },
  {
    "name": "dd",
    "email": "onyekwerehenry@gmail.com",
    "date": "2025-02-27T13:31:27.639Z"
  },
  {
    "name": "dd",
    "email": "onyekwerehenry@gmail.com",
    "date": "2025-02-27T13:33:20.288Z"
  },
  {
    "name": "dcvdv",
    "email": "onyekwerehenry@gmail.com",
    "date": "2025-02-27T13:34:45.237Z"
  },
  {
    "name": "Collins",
    "email": "onyekwerehenry@gmail.com",
    "date": "2025-02-27T13:38:27.822Z"
  },
  {
    "name": "Collins",
    "email": "Collins@gmail.com",
    "date": "2025-02-27T13:42:27.325Z"
  },
  {
    "name": "Collins",
    "email": "Collins@gmail.com",
    "date": "2025-02-27T13:43:28.551Z"
  },
  {
    "name": "Collins",
    "email": "Collins@gmail.com",
    "message": "Hope this works ",
    "ip": "::1",
    "device": "Chrome 133.0.0 / Windows 10.0.0 (Windows 10.0.0)",
    "date": "2025-02-27T14:03:21.722Z"
  },
  {
    "name": "Collins",
    "email": "Collins@gmail.com",
    "message": "erge",
    "ip": "::1",
    "device": "Chrome 133.0.0 / Windows 10.0.0 (Windows 10.0.0)",
    "date": "2025-02-27T14:14:40.878Z"
  },
  {
    "name": "Onyekwere Henry",
    "email": "onyekwereh6@gmail",
    "message": "hello",
    "ip": "::1",
    "device": "Chrome 133.0.0 / Windows 10.0.0 (Windows 10.0.0)",
    "date": "2025-02-27T14:21:31.781Z"
  },
  {
    "name": "Onyekwere Henry",
    "email": "dandaveudoka@gmail.com",
    "message": "hiii",
    "ip": "::1",
    "device": "Chrome 133.0.0 / Windows 10.0.0 (Windows 10.0.0)",
    "date": "2025-02-27T14:24:49.403Z"
  },
  {
    "name": "Sir Dunamix",
    "email": "techwithdunamix@gmail.com",
    "message": "hi my name is daniel , and together with henry we are gay as fuck",
    "ip": "::1",
    "device": "Chrome 133.0.0 / Windows 10.0.0 (Windows 10.0.0)",
    "date": "2025-02-27T14:27:48.248Z"
  },
  {
    "name": "Sir Dunamix",
    "email": "techwithdunamix@gmail.com",
    "message": "please we aint gay thanks",
    "ip": "::1",
    "device": "Chrome 133.0.0 / Windows 10.0.0 (Windows 10.0.0)",
    "date": "2025-02-27T15:02:35.087Z"
  },
  {
    "name": "Onyekwere Henry",
    "email": "onyekwereh6@gmail.com",
    "message": "helo big guy",
    "ip": "::1",
    "device": "Chrome 133.0.0 / Windows 10.0.0 (Windows 10.0.0)",
    "date": "2025-02-27T15:05:43.162Z"
  },
  {
    "name": "Sir Dunamix",
    "email": "techwithdunamix@gmail.com",
    "message": "we aint gay please",
    "ip": "::1",
    "device": "Chrome 133.0.0 / Windows 10.0.0 (Windows 10.0.0)",
    "date": "2025-02-27T15:08:14.163Z"
  },
  {
    "name": "Sir Dunamix",
    "email": "techwithdunamix@gmail.com",
    "message": "gfbgfh",
    "ip": "::1",
    "device": "Chrome 133.0.0 / Windows 10.0.0 (Windows 10.0.0)",
    "date": "2025-02-27T15:26:40.933Z"
  },
  {
    "name": "Sir Dunamix",
    "email": "techwithdunamix@gmail.com",
    "message": "big guy",
    "ip": "::1",
    "device": "Chrome 133.0.0 / Windows 10.0.0 (Windows 10.0.0)",
    "date": "2025-02-27T15:31:00.836Z"
  },
  {
    "name": "Onyekwere Henry",
    "email": "onyekwereh6@gmail.com",
    "message": "helo big guy",
    "ip": "::1",
    "device": "Chrome 133.0.0 / Windows 10.0.0 (Windows 10.0.0)",
    "date": "2025-02-27T15:31:23.829Z"
  },
  {
    "name": "Onyekwere Henry",
    "email": "onyekwereh6@gmail.com",
    "message": "helo big guy",
    "ip": "::1",
    "device": "Chrome 133.0.0 / Windows 10.0.0 (Windows 10.0.0)",
    "date": "2025-02-27T15:31:44.258Z"
  },
  {
    "name": "Onyekwere Henry",
    "email": "onyekwereh6@gmail.com",
    "message": "helo big guy",
    "ip": "::1",
    "device": "Chrome 133.0.0 / Windows 10.0.0 (Windows 10.0.0)",
    "date": "2025-02-27T15:32:39.645Z"
  },
  {
    "name": "Onyekwere Henry",
    "email": "onyekwereh6@gmail.com",
    "message": "helo big guy",
    "ip": "::1",
    "device": "Chrome 133.0.0 / Windows 10.0.0 (Windows 10.0.0)",
    "date": "2025-02-27T15:32:57.458Z"
  },
  {
    "name": "Onyekwere Henry",
    "email": "onyekwereh6@gmail.com",
    "message": "helo big guy",
    "ip": "::1",
    "device": "Chrome 133.0.0 / Windows 10.0.0 (Windows 10.0.0)",
    "date": "2025-02-27T15:35:49.160Z"
  },
  {
    "name": "Onyekwere Henry",
    "email": "onyekwereh6@gmail.com",
    "message": "helo big guy",
    "ip": "::1",
    "device": "Chrome 133.0.0 / Windows 10.0.0 (Windows 10.0.0)",
    "date": "2025-02-27T15:37:12.785Z"
  },
  {
    "name": "Onyekwere Henry",
    "email": "onyekwereh6@gmail.com",
    "message": "sdd",
    "ip": "::1",
    "device": "Chrome 133.0.0 / Windows 10.0.0 (Windows 10.0.0)",
    "date": "2025-02-27T15:37:47.726Z"
  },
  {
    "name": "Onyekwere Henry",
    "email": "onyekwereh6@gmail.com",
    "message": "helo big guy",
    "ip": "::1",
    "device": "Chrome 133.0.0 / Windows 10.0.0 (Windows 10.0.0)",
    "date": "2025-02-27T15:41:23.160Z"
  },
  {
    "name": "Onyekwere Henry",
    "email": "onyekwerehenry@gmail.com",
    "message": "hi",
    "ip": "::1",
    "device": "Chrome 133.0.0 / Windows 10.0.0 (Windows 10.0.0)",
    "date": "2025-02-27T16:07:36.182Z"
  },
  {
    "name": "udolka",
    "email": "udolka@gmail.com",
    "message": "udolkarr",
    "ip": "::ffff:127.0.0.1",
    "device": "Other 0.0.0 / Other 0.0.0 (Other 0.0.0)",
    "date": "2025-02-27T16:28:02.356Z"
  },
  {
    "name": "Sir Dunamix",
    "email": "techwithdunamix@gmail.com",
    "message": "oya give me your ip osis",
    "ip": "::1",
    "device": "Chrome 133.0.0 / Windows 10.0.0 (Windows 10.0.0)",
    "date": "2025-02-27T16:59:12.799Z"
  },
  {
    "name": "fvbfb",
    "email": "djdvj@gmail.com",
    "message": "ghgt",
    "ip": "::1",
    "device": "Chrome 133.0.0 / Windows 10.0.0 (Windows 10.0.0)",
    "date": "2025-02-27T19:29:36.316Z"
  },
  {
    "name": "Sir Dunamix",
    "email": "techwithdunamix@gmail.com",
    "message": "cdvfdr",
    "ip": "::1",
    "device": "Chrome 133.0.0 / Windows 10.0.0 (Windows 10.0.0)",
    "date": "2025-02-27T19:46:46.481Z"
  },
  {
    "name": "Onyekwere Henry",
    "email": "onyekwerehenry@gmail.com",
    "message": "hello boss",
    "ip": "::1",
    "device": "Chrome 133.0.0 / Windows 10.0.0 (Windows 10.0.0)",
    "location": "undefined, undefined, undefined",
    "date": "2025-02-27T19:49:19.362Z"
  },
  {
    "name": "Onyekwere Henry",
    "email": "onyekwerehenry@gmail.com",
    "message": "hello",
    "ip": "::1",
    "device": "Chrome 133.0.0 / Windows 10.0.0 (Windows 10.0.0)",
    "location": "undefined, undefined, undefined",
    "date": "2025-02-27T20:28:20.726Z"
  },
  {
    "name": "Onyekwere Henry",
    "email": "onyekwerehenry@gmail.com",
    "message": "hello isi aki",
    "ip": "::1",
    "device": "Chrome 133.0.0 / Windows 10.0.0 (Windows 10.0.0)",
    "location": "undefined, undefined, undefined",
    "coordinates": {},
    "connection": "Wi-Fi",
    "date": "2025-02-27T20:41:55.877Z"
  },
  {
    "name": "Og wise milli",
    "email": "dandaveudoka@gmail.com",
    "message": "dewc",
    "ip": "::1",
    "device": "Chrome 133.0.0 / Mac OS X 10.15.7 (Mac OS X 10.15.7)",
    "location": "undefined, undefined, undefined",
    "coordinates": {},
    "connection": "Wi-Fi",
    "date": "2025-02-28T17:03:40.233Z"
  },
  {
    "name": "Og wise milli",
    "email": "dandaveudoka@gmail.com",
    "mobile": "Not provided",
    "message": "hiii",
    "ip": "::1",
    "device": "Chrome 133.0.0 / Mac OS X 10.15.7 (Mac OS X 10.15.7)",
    "location": "undefined, undefined, undefined",
    "coordinates": {},
    "connection": "Wi-Fi",
    "date": "2025-03-01T20:55:09.009Z"
  },
  {
    "name": "Og wise milli",
    "email": "dandaveudoka@gmail.com",
    "mobile": "Not provided",
    "message": "hi",
    "ip": "::1",
    "device": "Chrome 133.0.0 / Mac OS X 10.15.7 (Mac OS X 10.15.7)",
    "location": "undefined, undefined, undefined",
    "coordinates": {},
    "connection": "Wi-Fi",
    "date": "2025-03-01T21:06:24.777Z"
  },
  {
    "name": "Og wise milli",
    "email": "dandaveudoka@gmail.com",
    "mobile": "Not provided",
    "message": "hello",
    "ip": "::1",
    "device": "Chrome 133.0.0 / Mac OS X 10.15.7 (Mac OS X 10.15.7)",
    "location": "undefined, undefined, undefined",
    "coordinates": {},
    "connection": "Wi-Fi",
    "date": "2025-03-01T23:23:59.149Z"
  },
  {
    "name": "Og wise milli",
    "email": "dandaveudoka@gmail.com",
    "mobile": "Not provided",
    "message": "hi",
    "ip": "::1",
    "device": "Chrome 133.0.0 / Mac OS X 10.15.7 (Mac OS X 10.15.7)",
    "location": "undefined, undefined, undefined",
    "coordinates": {},
    "connection": "Wi-Fi",
    "date": "2025-03-02T00:20:16.176Z"
  },
  {
    "name": "Udoka Dandave",
    "email": "dandaveudoka@gmail.com",
    "mobile": "Not provided",
    "message": "gu",
    "ip": "::1",
    "device": "Chrome 133.0.0 / Mac OS X 10.15.7 (Mac OS X 10.15.7)",
    "location": "undefined, undefined, undefined",
    "coordinates": {},
    "connection": "Wi-Fi",
    "date": "2025-03-02T17:41:03.961Z"
  },
  {
    "name": "Udoka Dandave",
    "email": "dandaveudoka@gmail.com",
    "mobile": "Not provided",
    "message": "hii",
    "ip": "::1",
    "device": "Chrome 133.0.0 / Mac OS X 10.15.7 (Mac OS X 10.15.7)",
    "location": "undefined, undefined, undefined",
    "coordinates": {},
    "connection": "Wi-Fi",
    "date": "2025-03-02T17:53:53.589Z"
  },
  {
    "name": "Udoka Dandave",
    "email": "dandaveudoka@gmail.com",
    "mobile": "Not provided",
    "message": "hi",
    "ip": "::1",
    "device": "Chrome 133.0.0 / Mac OS X 10.15.7 (Mac OS X 10.15.7)",
    "location": "undefined, undefined, undefined",
    "coordinates": {},
    "connection": "Wi-Fi",
    "date": "2025-03-02T18:48:14.964Z"
  },
  {
    "name": "Udoka Dandave",
    "email": "dandaveudoka@gmail.com",
    "mobile": "Not provided",
    "message": "hi",
    "ip": "::1",
    "device": "Chrome Mobile 133.0.0 / Android 6.0.0 (Android 6.0.0)",
    "location": "undefined, undefined, undefined",
    "coordinates": {},
    "connection": "Wi-Fi",
    "date": "2025-03-02T19:38:46.850Z"
  },
  {
    "name": "Udoka Dandave",
    "email": "dandaveudoka@gmail.com",
    "mobile": "Not provided",
    "message": "hello",
    "ip": "::1",
    "device": "Chrome Mobile 133.0.0 / Android 6.0.0 (Android 6.0.0)",
    "location": "undefined, undefined, undefined",
    "coordinates": {},
    "connection": "Wi-Fi",
    "date": "2025-03-05T04:42:05.874Z"
  }
]